__init__.py
sinapsis_mem0/helpers/__init__.py
sinapsis_mem0/helpers/env_var_keys.py
sinapsis_mem0/helpers/tags.py
sinapsis_mem0/templates/__init__.py
sinapsis_mem0/templates/mem0_add.py
sinapsis_mem0/templates/mem0_base.py
sinapsis_mem0/templates/mem0_delete.py
sinapsis_mem0/templates/mem0_get.py
sinapsis_mem0/templates/mem0_reset.py
sinapsis_mem0/templates/mem0_search.py
sinapsis_mem0-0.1.5.dist-info/licenses/LICENSE
sinapsis_mem0-0.1.5.dist-info/METADATA
sinapsis_mem0-0.1.5.dist-info/WHEEL
sinapsis_mem0-0.1.5.dist-info/top_level.txt
sinapsis_mem0-0.1.5.dist-info/RECORD
