Metadata-Version: 2.4
Name: sinapsis-mem0
Version: 0.1.5
Summary: Sinapsis templates for LLM memory management.
Author-email: SinapsisAI <dev@sinapsis.tech>
Project-URL: Homepage, https://sinapsis.tech
Project-URL: Documentation, https://docs.sinapsis.tech/docs
Project-URL: Tutorials, https://docs.sinapsis.tech/tutorials
Project-URL: Repository, https://github.com/Sinapsis-AI/sinapsis-chatbots.git
Requires-Python: >=3.10
License-File: LICENSE
Requires-Dist: mem0ai>=0.1.100
Requires-Dist: sinapsis>=0.2.10
Provides-Extra: graph
Requires-Dist: mem0ai[graph]>=0.1.100; extra == "graph"
Provides-Extra: all
Requires-Dist: sinapsis-mem0[graph]; extra == "all"
Dynamic: license-file
